aioretry/__init__.py
aioretry/py.typed
aioretry/retry.py
aioretry-6.3.0.dist-info/LICENSE
aioretry-6.3.0.dist-info/METADATA
aioretry-6.3.0.dist-info/WHEEL
aioretry-6.3.0.dist-info/top_level.txt
aioretry-6.3.0.dist-info/RECORD
